README.md
setup.py
online_learning_computations.egg-info/PKG-INFO
online_learning_computations.egg-info/SOURCES.txt
online_learning_computations.egg-info/dependency_links.txt
online_learning_computations.egg-info/requires.txt
online_learning_computations.egg-info/top_level.txt
scripts/__init__.py
scripts/computeIntsFromIpStrings.py
src/__init__.py
src/engagement.py
src/test/__init__.py
src/test/testEngagement.py