Metadata-Version: 1.0
Name: online-learning-computations
Version: 0.35
Summary: Computes statistics from OpenEdX platform data.
Home-page: https://github.com/paepcke/online_learning_computations
Author: Andreas Paepcke
Author-email: UNKNOWN
License: BSD
Keywords: OpenEdX,learning science
Platform: UNKNOWN
